brain_striatum_seg/__init__.py
brain_striatum_seg/cli.py
brain_striatum_seg/config.py
brain_striatum_seg/download.py
brain_striatum_seg/predictor.py
brain_striatum_seg/python_api.py
brain_striatum_seg/utils.py
brain_striatum_seg/resources/model_urls.json
brain_striatum_seg-1.0.0.dist-info/licenses/LICENSE
brain_striatum_seg-1.0.0.dist-info/METADATA
brain_striatum_seg-1.0.0.dist-info/WHEEL
brain_striatum_seg-1.0.0.dist-info/entry_points.txt
brain_striatum_seg-1.0.0.dist-info/top_level.txt
brain_striatum_seg-1.0.0.dist-info/RECORD
